[
    {
        "_id": 1001,
        "userName": "John Michael",
        "userImg": "https://preview.keenthemes.com/metronic-v4/theme/assets/pages/media/profile/profile_user.jpg",
        "review": "I've bought CarsArena headlights 6 months ago and it's really a good product.",
        "millTime": 1653497139790,
        "date": "May 18, 2022",
        "rating": 4.00
    },

    {
        "_id": 1002,
        "userName": "Ashley Nurse",
        "userImg": "https://images.unsplash.com/photo-1494790108377-be9c29b29330?ixlib=rb-1.2.1&ixid=MnwxMjA3fDB8MHxwaG90by1wYWdlfHx8fGVufDB8fHx8&auto=format&fit=crop&w=687&q=80",
        "review": "I've bought CarsArena spoiler and it's really a quality & cool product.",
        "millTime": 1653497139710,
        "date": "May 17, 2022",
        "rating": 4.50
    },

    {
        "_id": 1003,
        "userName": "Joseph Gonzalez",
        "userImg": "https://images.unsplash.com/photo-1507003211169-0a1dd7228f2d?ixlib=rb-1.2.1&ixid=MnwxMjA3fDB8MHxwaG90by1wYWdlfHx8fGVufDB8fHx8&auto=format&fit=crop&w=687&q=80",
        "review": "I've bought CarsArena tires and it is one of the best selling product of CarsArena.",
        "millTime": 1653497139752,
        "date": "May 15, 2022",
        "rating": 4.25
    },

    {
        "_id": 1004,
        "userName": "Hailey Reed",
        "userImg": "https://images.unsplash.com/photo-1520454125516-134a66d9bf78?ixlib=rb-1.2.1&ixid=MnwxMjA3fDB8MHxwaG90by1wYWdlfHx8fGVufDB8fHx8&auto=format&fit=crop&w=687&q=80",
        "review": "I've bought CarsArena gearbox and it is absolutely top notch product.",
        "millTime": 1653497139730,
        "date": "May 11, 2022",
        "rating": 4.75
    },

    {
        "_id": 1005,
        "userName": "Taylor Wright",
        "userImg": "https://images.unsplash.com/photo-1517630800677-932d836ab680?ixlib=rb-1.2.1&ixid=MnwxMjA3fDB8MHxwaG90by1wYWdlfHx8fGVufDB8fHx8&auto=format&fit=crop&w=687&q=80",
        "review": "I have bought CarsArena rims some days ago an it is one of the best selling product of my shop. Highly recommended!!!",
        "millTime": 1653497139740,
        "date": "May 20, 2022",
        "rating": 4.50
    },

    {
        "_id": 1006,
        "userName": "Gwendal Cottin",
        "userImg": "https://images.unsplash.com/photo-1525873765963-8931ab571545?ixlib=rb-1.2.1&ixid=MnwxMjA3fDB8MHxwaG90by1wYWdlfHx8fGVufDB8fHx8&auto=format&fit=crop&w=687&q=80",
        "review": "I have bought CarsArena Transmission 3 months ago. I ordered 150 units all are sold in this time span. They are really selling top notch product.",
        "millTime": 1653497139737,
        "date": "May 21, 2022",
        "rating": 5.00
    }
]